[ {
  "id" : "81a87030-de13-bd81-6c57-f66eb3420300",
  "name" : "button_style",
  "display_width" : null,
  "label" : "Button style",
  "required" : false,
  "locked" : false,
  "display" : "select",
  "choices" : [ [ "primary", "PRIMARY" ], [ "secondary", "SECONDARY" ], [ "territory", "TERRITORY" ], [ "simple", "SIMPLE" ] ],
  "multiple" : false,
  "reordering_enabled" : true,
  "preset" : null,
  "type" : "choice",
  "default" : "primary"
}, {
  "id" : "db5e9748-c088-4bd3-77a3-55026e13aa8c",
  "name" : "styles_overwrite",
  "display_width" : null,
  "label" : "Styles overwrite",
  "help_text" : "You can apply button background and text color instead of default color.",
  "required" : false,
  "locked" : false,
  "display" : "toggle",
  "type" : "boolean",
  "default" : false
}, {
  "id" : "9dc7026c-fc2f-1a9b-b5a4-0c346986e25f",
  "name" : "button_link",
  "display_width" : null,
  "label" : "Button link",
  "required" : false,
  "locked" : false,
  "supported_types" : [ "EXTERNAL", "CONTENT", "FILE", "EMAIL_ADDRESS", "BLOG", "CALL_TO_ACTION", "PHONE_NUMBER", "WHATSAPP_NUMBER" ],
  "show_advanced_rel_options" : false,
  "type" : "link",
  "default" : {
    "url" : {
      "content_id" : null,
      "type" : "EXTERNAL",
      "href" : ""
    },
    "open_in_new_tab" : false,
    "no_follow" : false
  }
}, {
  "id" : "4ebaf16e-fc0b-a54a-ce5b-f2e6e0ae69fa",
  "name" : "button_text",
  "display_width" : null,
  "label" : "Button text",
  "required" : false,
  "locked" : false,
  "validation_regex" : "",
  "allow_new_line" : false,
  "show_emoji_picker" : false,
  "type" : "text",
  "default" : "Label"
}, {
  "id" : "d467f2c9-2f0c-c45f-e448-a6c560342b86",
  "name" : "button_text_color",
  "display_width" : null,
  "label" : "Button text Color",
  "required" : false,
  "locked" : false,
  "visibility" : {
    "controlling_field" : null,
    "controlling_field_path" : "styles_overwrite",
    "controlling_value_regex" : "true",
    "property" : null,
    "operator" : "EQUAL",
    "access" : null
  },
  "show_opacity" : false,
  "type" : "color",
  "default" : {
    "color" : "#FFFFFF",
    "opacity" : 100
  }
}, {
  "id" : "9e9ce6aa-4f94-27d7-1979-5b782326647e",
  "name" : "font_bold",
  "display_width" : null,
  "label" : "Font bold",
  "required" : false,
  "locked" : false,
  "display" : "toggle",
  "type" : "boolean",
  "default" : true
}, {
  "id" : "c74ae235-1bc8-032e-76a5-da3cc1c81a28",
  "name" : "button_border_color",
  "display_width" : null,
  "label" : "Button border color",
  "required" : false,
  "locked" : false,
  "visibility" : {
    "controlling_field" : null,
    "controlling_field_path" : "styles_overwrite",
    "controlling_value_regex" : "true",
    "property" : null,
    "operator" : "EQUAL",
    "access" : null
  },
  "type" : "color",
  "default" : {
    "color" : "#00A2AF",
    "opacity" : 100
  }
}, {
  "id" : "0ce53e9a-090a-d8d0-20fc-204288d8966d",
  "name" : "button_background_color",
  "display_width" : null,
  "label" : "Button background color",
  "required" : false,
  "locked" : false,
  "visibility" : {
    "controlling_field" : null,
    "controlling_field_path" : "styles_overwrite",
    "controlling_value_regex" : "true",
    "property" : null,
    "operator" : "EQUAL",
    "access" : null
  },
  "type" : "color",
  "default" : {
    "color" : "#00A2AF",
    "opacity" : 100
  }
}, {
  "id" : "5a302bf8-1ead-d4c9-d5a2-232a3f37b9e0",
  "name" : "button_alignment",
  "display_width" : null,
  "label" : "Button alignment",
  "required" : false,
  "locked" : false,
  "display" : "radio",
  "choices" : [ [ "left", "Left" ], [ "center", "Center" ], [ "right", "Right" ] ],
  "multiple" : false,
  "reordering_enabled" : true,
  "preset" : null,
  "type" : "choice",
  "default" : "left"
} ]